progressive_py/__init__.py
progressive_py/manager.py
progressive_py/ntbk_progbar.py
progressive_py/ntbk_spinner.py
progressive_py/progress_bar.py
progressive_py/spinner.py
progressive_py/utils.py
progressive_py/assets/ntbk_spinner/file
progressive_py/assets/ntbk_spinner/style.json
progressive_py/assets/ntbk_spinner/theme.json
progressive_py/assets/progress_bar/f
progressive_py/assets/progress_bar/style.json
progressive_py/assets/progress_bar/theme.json
progressive_py/assets/spinner/f
progressive_py/assets/spinner/style.json
progressive_py/assets/spinner/theme.json
progressive_py-0.1.4.dist-info/METADATA
progressive_py-0.1.4.dist-info/WHEEL
progressive_py-0.1.4.dist-info/top_level.txt
progressive_py-0.1.4.dist-info/RECORD
