Metadata-Version: 2.4
Name: progressive_py
Version: 0.1.4
Summary: Elegant, customizable progress bars and spinners for Python — in both terminal and Jupyter notebook environments!
Author-email: Muhammad Abubakar Siddique Ansari <ansaricodes@gmail.com>
Project-URL: Homepage, https://github.com/Ansari-Codes/progressive_py.git
Requires-Python: >=3.6
Requires-Dist: IPython
Requires-Dist: colorama>=0.4.6
